{"lastUsed":1734129615619,"path":"\/Users\/igornegrao\/Documents\/java-estudos","projectCount":3,"recentFiles":[{"path":"\/exceptionRuim\/src\/application","parentWorkspace":"\/Users\/igornegrao\/Documents\/java-estudos","name":"Program.java","lastModified":1734127828993,"locationURI":"file:\/Users\/igornegrao\/Documents\/java-estudos\/exceptionRuim\/src\/application\/Program.java"},{"path":"\/exceptionMenosRuim\/src\/model\/entities","parentWorkspace":"\/Users\/igornegrao\/Documents\/java-estudos","name":"Reservation.java","lastModified":1734129462855,"locationURI":"file:\/Users\/igornegrao\/Documents\/java-estudos\/exceptionMenosRuim\/src\/model\/entities\/Reservation.java"},{"path":"\/exceptionRuim\/src\/model\/entities","parentWorkspace":"\/Users\/igornegrao\/Documents\/java-estudos","name":"Reservation.java","lastModified":1734127793986,"locationURI":"file:\/Users\/igornegrao\/Documents\/java-estudos\/exceptionRuim\/src\/model\/entities\/Reservation.java"},{"path":"\/trycath01\/src\/application","parentWorkspace":"\/Users\/igornegrao\/Documents\/java-estudos","name":"Program.java","lastModified":1734015906058,"locationURI":"file:\/Users\/igornegrao\/Documents\/java-estudos\/trycath01\/src\/application\/Program.java"},{"path":"\/exceptionMenosRuim\/src\/application","parentWorkspace":"\/Users\/igornegrao\/Documents\/java-estudos","name":"Program.java","lastModified":1734129615620,"locationURI":"file:\/Users\/igornegrao\/Documents\/java-estudos\/exceptionMenosRuim\/src\/application\/Program.java"}]}